assistants/__init__.py
assistants/build.py
assistants/chatgpt.py
assistants/claude.py
assistants/main.py
assistants/main_bot_conversation.py
assistants/main_tg.py
assistants/version.py
assistants/ai/__init__.py
assistants/ai/anthropic.py
assistants/ai/constants.py
assistants/ai/dummy_assistant.py
assistants/ai/memory.py
assistants/ai/mistral.py
assistants/ai/openai.py
assistants/ai/types.py
assistants/ai/universal.py
assistants/cli/__init__.py
assistants/cli/arg_parser.py
assistants/cli/assistant_config.py
assistants/cli/cli.py
assistants/cli/commands.py
assistants/cli/fs.py
assistants/cli/help.py
assistants/cli/io_loop.py
assistants/cli/output.py
assistants/cli/prompt.py
assistants/cli/selector.py
assistants/cli/terminal.py
assistants/cli/utils.py
assistants/config/__init__.py
assistants/config/file_management.py
assistants/lib/__init__.py
assistants/lib/constants.py
assistants/lib/exceptions.py
assistants/log/__init__.py
assistants/log/logging/__init__.py
assistants/log/logging/_loguru_logger.py
assistants/telegram_ui/__init__.py
assistants/telegram_ui/auth.py
assistants/telegram_ui/bot_conversation_bot.py
assistants/telegram_ui/commands.py
assistants/telegram_ui/lib.py
assistants/telegram_ui/tg_bot.py
assistants/user_data/__init__.py
assistants/user_data/interfaces/__init__.py
assistants/user_data/interfaces/telegram_chat_data.py
assistants/user_data/sqlite_backend/__init__.py
assistants/user_data/sqlite_backend/conversations.py
assistants/user_data/sqlite_backend/message.py
assistants/user_data/sqlite_backend/table.py
assistants/user_data/sqlite_backend/telegram_chat_data.py
assistants_framework-0.9.0.dist-info/METADATA
assistants_framework-0.9.0.dist-info/WHEEL
assistants_framework-0.9.0.dist-info/entry_points.txt
assistants_framework-0.9.0.dist-info/licenses/LICENSE
assistants_framework-0.9.0.dist-info/RECORD
