Metadata-Version: 2.4
Name: assistants-framework
Version: 0.9.0
Summary: AI Assistant Framework with CLI and Telegram Bot
Project-URL: Homepage, https://github.com/nihilok/assistants
Project-URL: Bug Tracker, https://github.com/nihilok/assistants/issues
Author-email: Michael Jarvis <nihilok@jarv.dev>
License: MIT License
License-File: LICENSE
Keywords: anthropic,assistant,assistants,bot,chatbot,chatgpt,claude,cli,coding,coding-assistant,deepseek,gpt3,gpt3.5,gpt4,gpt5,llm,mistral,o1,o4,openai,programming,telegram,tui,ui
Classifier: License :: OSI Approved :: MIT License
Classifier: Operating System :: OS Independent
Classifier: Programming Language :: Python :: 3
Requires-Python: >=3.10
Requires-Dist: aiofiles==24.1.0
Requires-Dist: aiohttp==3.12.15
Requires-Dist: aiosqlite==0.21.0
Requires-Dist: loguru==0.7.3
Requires-Dist: prompt-toolkit==3.0.52
Requires-Dist: pydantic~=2.11.5
Requires-Dist: pygments-tsx==1.0.3
Requires-Dist: pyperclip==1.11.0
Requires-Dist: pyyaml==6.0.3
Requires-Dist: setproctitle==1.3.7
Requires-Dist: tiktoken==0.11.0
Requires-Dist: types-aiofiles~=24.1.0.20250606
Requires-Dist: types-pygments~=2.19.0.20250516
Requires-Dist: types-pyyaml~=6.0.12.20250516
Requires-Dist: univllm==0.1.11
